pytesting_utils/__init__.py
pytesting_utils/context_managers.py
pytesting_utils/preconditions.py
pytesting_utils/py.typed
pytesting_utils/virtual_environment.py
pytesting_utils-0.5.0.dist-info/LICENSE.txt
pytesting_utils-0.5.0.dist-info/WHEEL
pytesting_utils-0.5.0.dist-info/METADATA
pytesting_utils-0.5.0.dist-info/RECORD
