Metadata-Version: 2.1
Name: pytesting-utils
Version: 0.5.0
Summary: Utilities for the PyTesting project
Home-page: https://github.com/pytesting/utils
License: LGPL-3.0+
Keywords: test runner,unittest,nose,pytest
Author: Stephan Lukasczyk
Author-email: python-test-runner@googlegroups.com
Requires-Python: >=3.6,<4.0
Classifier: Development Status :: 3 - Alpha
Classifier: Intended Audience :: Developers
Classifier: Intended Audience :: Education
Classifier: Intended Audience :: Science/Research
Classifier: License :: OSI Approved :: GNU Lesser General Public License v3 or later (LGPLv3+)
Classifier: Operating System :: POSIX :: Linux
Classifier: Programming Language :: Python
Classifier: Programming Language :: Python :: 3
Classifier: Programming Language :: Python :: 3 :: Only
Classifier: Programming Language :: Python :: 3.6
Classifier: Programming Language :: Python :: 3.7
Classifier: Programming Language :: Python :: 3.8
Classifier: Topic :: Education
Classifier: Topic :: Education :: Testing
Classifier: Topic :: Software Development
Classifier: Topic :: Software Development :: Testing
Classifier: Topic :: Software Development :: Testing :: Unit
Classifier: Topic :: Utilities
Requires-Dist: virtualenv (>=16.7,<17.0)
Project-URL: Repository, https://github.com/pytesting/utils
